{
  "exercises": [
    {
      "sentences": [
        {
          "number": 1,
          "original_sentence": "They gave the oldest councillor the freedom of the city.",
          "keyword": "given",
          "gapped_sentence": "The oldest councillor ................................. the freedom of the city.",
          "answers": [
            "should have been given",
            "must have been given"
          ]
        },
        {
          "number": 2,
          "original_sentence": "They denied access to the secret documents to all but a few.",
          "keyword": "been",
          "gapped_sentence": "All but a few ................................. access to the secret documents.",
          "answers": [
            "should have been denied",
            "must have been denied"
          ]
        },
        {
          "number": 3,
          "original_sentence": "Someone showed the child how to use the telephone.",
          "keyword": "have",
          "gapped_sentence": "The child ................................. how to use the telephone.",
          "answers": [
            "should have been shown",
            "must have been shown",
            "could have been shown"
          ]
        },
        {
          "number": 4,
          "original_sentence": "They declared him 'persona non grata' and allowed him only forty-eight hours to leave the country.",
          "keyword": "been",
          "gapped_sentence": "He ................................. 'persona non grata' and allowed only forty-eight hours to leave the country.",
          "answers": [
            "must have been declared",
            "should have been declared"
          ]
        },
        {
          "number": 5,
          "original_sentence": "They gave him artificial respiration.",
          "keyword": "been",
          "gapped_sentence": "He ................................. artificial respiration.",
          "answers": [
            "should have been given",
            "must have been given",
            "ought to have been given"
          ]
        },
        {
          "number": 6,
          "original_sentence": "Why didn't they offer him the job?",
          "keyword": "not",
          "gapped_sentence": "Why ................................. the job?",
          "answers": [
            "should he not have been offered",
            "could he not have been offered"
          ]
        }
      ]
    },
    {
      "sentences": [
        {
          "number": 7,
          "original_sentence": "Didn't they promise you a rise in salary at the beginning of the year?",
          "keyword": "have",
          "gapped_sentence": "................................. a rise in salary at the beginning of the year?",
          "answers": [
            "should you not have been promised",
            "shouldn't you have been promised"
          ]
        },
        {
          "number": 8,
          "original_sentence": "Someone left him a legacy of £10,000.",
          "keyword": "have",
          "gapped_sentence": "He ................................. a legacy of £10,000.",
          "answers": [
            "must have been left",
            "should have been left"
          ]
        },
        {
          "number": 9,
          "original_sentence": "When he looked at the stamps, he found they had sold him forgeries.",
          "keyword": "been",
          "gapped_sentence": "When he looked at the stamps, he found he ................................. forgeries.",
          "answers": [
            "must have been sold",
            "could have been sold"
          ]
        },
        {
          "number": 10,
          "original_sentence": "What did they pay you for doing the job?",
          "keyword": "been",
          "gapped_sentence": "What ................................. for doing the job?",
          "answers": [
            "should you have been paid"
          ]
        },
        {
          "number": 11,
          "original_sentence": "Someone should tell him never to do that again.",
          "keyword": "be",
          "gapped_sentence": "He ................................. never to do that again.",
          "answers": [
            "ought to be told",
            "should be told"
          ]
        },
        {
          "number": 12,
          "original_sentence": "They asked you to meet me here at 11 o'clock, not half-past.",
          "keyword": "have",
          "gapped_sentence": "You ................................. to meet me here at 11 o'clock, not half-past.",
          "answers": [
            "should have been asked"
          ]
        }
      ]
    },
    {
      "sentences": [
        {
          "number": 13,
          "original_sentence": "Will someone send me the details?",
          "keyword": "be",
          "gapped_sentence": "................................. the details?",
          "answers": [
            "will i be sent",
            "shall i be sent"
          ]
        },
        {
          "number": 14,
          "original_sentence": "We shall send you the goods as soon as they are available.",
          "keyword": "be",
          "gapped_sentence": "You ................................. the goods as soon as they are available.",
          "answers": [
            "will be sent",
            "should be sent"
          ]
        },
        {
          "number": 15,
          "original_sentence": "Someone must teach that boy a lesson!",
          "keyword": "be",
          "gapped_sentence": "That boy ................................. a lesson!",
          "answers": [
            "must be taught",
            "ought to be taught"
          ]
        },
        {
          "number": 16,
          "original_sentence": "They gave up the search after three hours.",
          "keyword": "been",
          "gapped_sentence": "The search ................................. after three hours.",
          "answers": [
            "had to be given up",
            "should have been given up"
          ]
        },
        {
          "number": 17,
          "original_sentence": "They ought to have pointed that out to me at the very beginning.",
          "keyword": "been",
          "gapped_sentence": "That ................................. to me at the very beginning.",
          "answers": [
            "should have been pointed out",
            "ought to have been pointed out"
          ]
        },
        {
          "number": 18,
          "original_sentence": "No one brought up that question at the meeting.",
          "keyword": "been",
          "gapped_sentence": "That question ................................. at the meeting.",
          "answers": [
            "should have been brought up",
            "could have been brought up"
          ]
        }
      ]
    },
    {
      "sentences": [
        {
          "number": 19,
          "original_sentence": "Someone should look into the matter.",
          "keyword": "be",
          "gapped_sentence": "The matter ................................. into.",
          "answers": [
            "ought to be looked",
            "should be looked"
          ]
        },
        {
          "number": 20,
          "original_sentence": "It was clear that the parents had brought the child up well.",
          "keyword": "been",
          "gapped_sentence": "It was clear that the child ................................. up well.",
          "answers": [
            "must have been brought"
          ]
        },
        {
          "number": 21,
          "original_sentence": "We had to put off our visit until later.",
          "keyword": "be",
          "gapped_sentence": "Our visit ................................. until later.",
          "answers": [
            "had to be put off"
          ]
        },
        {
          "number": 22,
          "original_sentence": "I was shocked to hear that someone had broken into your house.",
          "keyword": "been",
          "gapped_sentence": "I was shocked to hear that your house ................................. into.",
          "answers": [
            "must have been broken",
            "could have been broken"
          ]
        },
        {
          "number": 23,
          "original_sentence": "Don't speak until someone speaks to you.",
          "keyword": "been",
          "gapped_sentence": "Don't speak until you ................................. to.",
          "answers": [
            "have been spoken"
          ]
        },
        {
          "number": 24,
          "original_sentence": "His bank manager turned down his request for a loan.",
          "keyword": "been",
          "gapped_sentence": "His request for a loan ................................. by his bank manager.",
          "answers": [
            "must have been turned down",
            "should have been turned down"
          ]
        }
      ]
    },
    {
      "sentences": [
        {
          "number": 25,
          "original_sentence": "You must account for every penny you spent.",
          "keyword": "be",
          "gapped_sentence": "Every penny you spent ................................. for.",
          "answers": [
            "must be accounted"
          ]
        },
        {
          "number": 26,
          "original_sentence": "Someone hasn't stuck this stamp on very firmly.",
          "keyword": "been",
          "gapped_sentence": "This stamp ................................. on very firmly.",
          "answers": [
            "does not appear to have been stuck",
            "doesn't appear to have been stuck",
            "cannot have been stuck"
          ]
        },
        {
          "number": 27,
          "original_sentence": "Events will bear out the truth of what I'm saying.",
          "keyword": "be",
          "gapped_sentence": "The truth of what I'm saying ................................. by events.",
          "answers": [
            "will be borne out"
          ]
        },
        {
          "number": 28,
          "original_sentence": "An official held us up at the Customs for half an hour.",
          "keyword": "been",
          "gapped_sentence": "We ................................. at the Customs for half an hour by an official.",
          "answers": [
            "must have been held up",
            "could have been held up"
          ]
        },
        {
          "number": 29,
          "original_sentence": "How can we bring about the desired result?",
          "keyword": "be",
          "gapped_sentence": "How can the desired result ................................. about?",
          "answers": [
            "be brought"
          ]
        },
        {
          "number": 30,
          "original_sentence": "He hates people making fun of him.",
          "keyword": "being",
          "gapped_sentence": "He hates ................................. of.",
          "answers": [
            "being made fun"
          ]
        }
      ]
    },
    {
      "sentences": [
        {
          "number": 31,
          "original_sentence": "The new washing machines turn out at the rate of fifty a day.",
          "keyword": "being",
          "gapped_sentence": "The new washing machines ................................. at the rate of fifty a day.",
          "answers": [
            "are being turned out"
          ]
        },
        {
          "number": 32,
          "original_sentence": "When her husband died, she naturally assumed that she would be provided for.",
          "keyword": "be",
          "gapped_sentence": "When her husband died, she naturally assumed that she ................................. for.",
          "answers": [
            "would be provided"
          ]
        },
        {
          "number": 33,
          "original_sentence": "I had my car serviced.",
          "keyword": "got",
          "gapped_sentence": "I ................................. serviced.",
          "answers": [
            "got my car"
          ]
        },
        {
          "number": 34,
          "original_sentence": "He had his arm broken while playing rugby.",
          "keyword": "got",
          "gapped_sentence": "He ................................. while playing rugby.",
          "answers": [
            "got his arm broken"
          ]
        },
        {
          "number": 35,
          "original_sentence": "He was knocked down by a car.",
          "keyword": "got",
          "gapped_sentence": "He ................................. by a car.",
          "answers": [
            "got knocked down"
          ]
        },
        {
          "number": 36,
          "original_sentence": "You should arrange to install central heating before winter comes.",
          "keyword": "have",
          "gapped_sentence": "You should ................................. before winter comes.",
          "answers": [
            "have central heating installed"
          ]
        }
      ]
    },
    {
      "sentences": [
        {
          "number": 37,
          "original_sentence": "He is arranging for an artist to paint his wife's portrait.",
          "keyword": "having",
          "gapped_sentence": "He is ................................. painted.",
          "answers": [
            "having his wife's portrait"
          ]
        },
        {
          "number": 38,
          "original_sentence": "They were made man and wife in 1980.",
          "keyword": "got",
          "gapped_sentence": "They ................................. in 1980.",
          "answers": [
            "got married"
          ]
        },
        {
          "number": 39,
          "original_sentence": "Five years later, they were no longer man and wife.",
          "keyword": "got",
          "gapped_sentence": "Five years later, they ................................. divorced.",
          "answers": [
            "got divorced",
            "had got divorced"
          ]
        },
        {
          "number": 40,
          "original_sentence": "Drive carefully if you don't want to risk the police endorsing your licence again.",
          "keyword": "have",
          "gapped_sentence": "Drive carefully if you don't want to ................................. again.",
          "answers": [
            "have your licence endorsed"
          ]
        },
        {
          "number": 41,
          "original_sentence": "The tree was so diseased that we had to ask someone to cut it down.",
          "keyword": "have",
          "gapped_sentence": "The tree was so diseased that we ................................. down.",
          "answers": [
            "had to have it cut"
          ]
        },
        {
          "number": 42,
          "original_sentence": "The authorities are encouraging mothers to arrange for the vaccination of their children.",
          "keyword": "get",
          "gapped_sentence": "The authorities are encouraging mothers to ................................. vaccinated.",
          "answers": [
            "get their children"
          ]
        }
      ]
    },
    {
      "sentences": [
        {
          "number": 43,
          "original_sentence": "Someone has written all the answers in this book.",
          "keyword": "have",
          "gapped_sentence": "This book ................................. all the answers written in it.",
          "answers": [
            "must have had",
            "appears to have had"
          ]
        },
        {
          "number": 44,
          "original_sentence": "She made an appointment with the optician for an examination of her eyes.",
          "keyword": "have",
          "gapped_sentence": "She made an appointment with the optician to ................................. examined.",
          "answers": [
            "have her eyes"
          ]
        },
        {
          "number": 45,
          "original_sentence": "Nobody would ever have beaten the champion if he had retired after his last fight.",
          "keyword": "have",
          "gapped_sentence": "The champion ................................. if he had retired after his last fight.",
          "answers": [
            "would never have got beaten",
            "could never have got beaten"
          ]
        },
        {
          "number": 46,
          "original_sentence": "The fact that the new scheme raised such a storm of disapproval means that no one can have explained it properly to the public.",
          "keyword": "been",
          "gapped_sentence": "The fact that the new scheme raised such a storm of disapproval means that it ................................. properly to the public.",
          "answers": [
            "cannot have been explained",
            "can't have been explained"
          ]
        },
        {
          "number": 47,
          "original_sentence": "His father warned him not to let others lead him astray.",
          "keyword": "be",
          "gapped_sentence": "His father warned him not to ................................. astray.",
          "answers": [
            "be led"
          ]
        },
        {
          "number": 48,
          "original_sentence": "The chairman of the committee complained that they were taking up too much time in discussing trivialities.",
          "keyword": "being",
          "gapped_sentence": "The chairman of the committee complained that too much time ................................. discussing trivialities.",
          "answers": [
            "was being spent"
          ]
        }
      ]
    },
    {
      "sentences": [
        {
          "number": 49,
          "original_sentence": "People put down the boy's rudeness to his parents' having spoiled him.",
          "keyword": "been",
          "gapped_sentence": "The boy's rudeness ................................. to his parents having spoiled him.",
          "answers": [
            "could have been put down",
            "must have been put down"
          ]
        },
        {
          "number": 50,
          "original_sentence": "Not until later did they discover that someone had stolen the picture.",
          "keyword": "been",
          "gapped_sentence": "Not until later did they discover that the picture ................................. stolen.",
          "answers": [
            "must have been",
            "had been"
          ]
        }
      ]
    }
  ]
}
