{
  "datasetName": "Useful Lists (B2)",
  "categories": {
    "Opinion & Discussion": {
      "icon": "💬",
      "type": "grouped",
      "items": [
        { "title": "In my opinion / view", "desc": "expressing personal viewpoint", "example": "In my opinion, online learning has many advantages." },
        { "title": "I believe / think that", "desc": "stating your belief", "example": "I believe that education should be free for everyone." },
        { "title": "From my perspective", "desc": "giving your point of view", "example": "From my perspective, the decision was correct." },
        { "title": "It seems to me that", "desc": "expressing tentative opinion", "example": "It seems to me that we need more time." },
        { "title": "As far as I'm concerned", "desc": "emphasizing personal view", "example": "As far as I'm concerned, it's the best solution." },
        { "title": "I would argue that", "desc": "presenting strong opinion", "example": "I would argue that technology has improved education." },
        { "title": "There's no doubt that", "desc": "expressing certainty", "example": "There's no doubt that climate change is real." },
        { "title": "It's widely believed that", "desc": "referring to common opinion", "example": "It's widely believed that exercise is beneficial." },
        { "title": "Many people claim that", "desc": "reporting others' opinions", "example": "Many people claim that social media is addictive." },
        { "title": "On the one hand / other hand", "desc": "presenting both sides", "example": "On the one hand it's expensive, but on the other hand it's effective." }
      ]
    },

    "Agreement & Disagreement": {
      "icon": "🤝",
      "type": "grouped",
      "items": [
        { "title": "I completely agree", "desc": "strong agreement", "example": "I completely agree with your point about education." },
        { "title": "I couldn't agree more", "desc": "strongest agreement", "example": "I couldn't agree more – this is exactly right." },
        { "title": "That's absolutely right", "desc": "confirming correctness", "example": "That's absolutely right, we need to act now." },
        { "title": "I'm afraid I disagree", "desc": "polite disagreement", "example": "I'm afraid I disagree with that analysis." },
        { "title": "I see your point, but", "desc": "acknowledging then disagreeing", "example": "I see your point, but I think there's another way." },
        { "title": "That's not necessarily true", "desc": "challenging statement", "example": "That's not necessarily true in all cases." },
        { "title": "I partly agree", "desc": "partial agreement", "example": "I partly agree, though some aspects need revision." },
        { "title": "Up to a point", "desc": "limited agreement", "example": "Up to a point, yes, but we must consider other factors." },
        { "title": "I'm not entirely convinced", "desc": "expressing doubt", "example": "I'm not entirely convinced by that argument." },
        { "title": "I beg to differ", "desc": "formal disagreement", "example": "I beg to differ on this particular matter." }
      ]
    },

    "Advantages & Disadvantages": {
      "icon": "⚖️",
      "type": "grouped",
      "items": [
        { "title": "One advantage / benefit is", "desc": "positive point", "example": "One advantage of online learning is flexibility." },
        { "title": "A major drawback / disadvantage", "desc": "negative point", "example": "A major drawback is the lack of face-to-face interaction." },
        { "title": "On the plus side", "desc": "informal positive point", "example": "On the plus side, it's much cheaper." },
        { "title": "On the downside", "desc": "informal negative point", "example": "On the downside, it requires a lot of self-discipline." },
        { "title": "The main benefit is that", "desc": "key positive aspect", "example": "The main benefit is that students can work at their own pace." },
        { "title": "A significant problem is", "desc": "important issue", "example": "A significant problem is the digital divide." },
        { "title": "It has the advantage of", "desc": "beneficial feature", "example": "It has the advantage of being accessible anywhere." },
        { "title": "The downside of this is", "desc": "negative element", "example": "The downside of this is increased screen time." },
        { "title": "One positive aspect is", "desc": "good feature", "example": "One positive aspect is the variety of resources available." },
        { "title": "A potential risk is", "desc": "possible danger", "example": "A potential risk is technology failure during exams." }
      ]
    },

    "Cause & Effect": {
      "icon": "🔗",
      "type": "grouped",
      "items": [
        { "title": "As a result / consequence", "desc": "showing result", "example": "As a result, many students improved their grades." },
        { "title": "This leads / led to", "desc": "causing something", "example": "This led to significant changes in teaching methods." },
        { "title": "Due to / Owing to", "desc": "because of (formal)", "example": "Due to the pandemic, schools moved online." },
        { "title": "This results in", "desc": "produces outcome", "example": "This results in better student engagement." },
        { "title": "Consequently", "desc": "therefore (formal)", "example": "Consequently, exam results have improved." },
        { "title": "For this reason", "desc": "explaining why", "example": "For this reason, we recommend this approach." },
        { "title": "This is why", "desc": "explaining cause", "example": "This is why many schools have changed policies." },
        { "title": "This has resulted in", "desc": "past consequence", "example": "This has resulted in higher enrollment numbers." },
        { "title": "The effect / impact of this", "desc": "describing consequences", "example": "The impact of this has been considerable." },
        { "title": "This can be attributed to", "desc": "identifying cause", "example": "This can be attributed to better training programs." }
      ]
    },

    "Time Expressions": {
      "icon": "⏰",
      "type": "simple",
      "items": [
        "currently", "at present", "nowadays", "these days", "recently", "lately",
        "in recent years", "previously", "formerly", "initially", "eventually",
        "subsequently", "simultaneously", "meanwhile", "in the meantime", "gradually",
        "progressively", "ultimately", "in the long run", "over time", "in the short term",
        "in due course", "from time to time", "on occasion", "periodically",
        "at regular intervals", "in the past", "historically"
      ]
    },

    "Frequency Adverbs": {
      "icon": "🔄",
      "type": "simple",
      "items": [
        "always", "constantly", "continually", "frequently", "regularly", "often",
        "generally", "usually", "normally", "typically", "commonly", "sometimes",
        "occasionally", "rarely", "seldom", "hardly ever", "scarcely", "never",
        "invariably", "consistently", "predominantly", "mainly", "mostly", "largely",
        "primarily"
      ]
    },

    "Describing Trends": {
      "icon": "📈",
      "type": "grouped",
      "items": [
        { "title": "increase / rise / grow", "desc": "go up", "example": "Sales have increased dramatically this year." },
        { "title": "decrease / decline / fall", "desc": "go down", "example": "Unemployment has declined steadily." },
        { "title": "remain stable / constant", "desc": "stay the same", "example": "Prices have remained stable." },
        { "title": "fluctuate", "desc": "go up and down", "example": "The market tends to fluctuate seasonally." },
        { "title": "peak / reach a peak", "desc": "highest point", "example": "Sales peaked in December." },
        { "title": "dramatically / sharply", "desc": "big change", "example": "Costs rose dramatically." },
        { "title": "gradually / steadily", "desc": "slow change", "example": "The economy has grown steadily." },
        { "title": "slightly / marginally", "desc": "small change", "example": "Profits increased slightly." },
        { "title": "experience a surge", "desc": "sudden increase", "example": "Demand experienced a surge." },
        { "title": "show a downward trend", "desc": "decreasing pattern", "example": "Statistics show a downward trend in smoking." }
      ]
    },

    "Expressing Probability": {
      "icon": "🎲",
      "type": "simple",
      "items": [
        "definitely", "certainly", "undoubtedly", "clearly", "obviously", "probably",
        "likely", "presumably", "apparently", "possibly", "perhaps", "maybe",
        "potentially", "conceivably", "arguably", "it's certain that",
        "it's probable that", "it's possible that", "in all likelihood",
        "the chances are that", "it's unlikely that", "there's a possibility that",
        "it appears that", "it seems that"
      ]
    },

    "Making Suggestions": {
      "icon": "💡",
      "type": "grouped",
      "items": [
        { "title": "I suggest / recommend that", "desc": "giving advice", "example": "I suggest that we meet earlier tomorrow." },
        { "title": "Why don't we / you", "desc": "informal suggestion", "example": "Why don't we take a break?" },
        { "title": "How about / What about", "desc": "proposing idea", "example": "How about trying a different approach?" },
        { "title": "We/You should / ought to", "desc": "giving advice", "example": "You should consider all the options." },
        { "title": "It might be a good idea to", "desc": "tentative suggestion", "example": "It might be a good idea to get professional advice." },
        { "title": "Have you considered", "desc": "suggesting alternative", "example": "Have you considered applying early?" },
        { "title": "It would be advisable to", "desc": "formal recommendation", "example": "It would be advisable to book in advance." },
        { "title": "My recommendation would be", "desc": "personal advice", "example": "My recommendation would be to start immediately." },
        { "title": "If I were you, I would", "desc": "hypothetical advice", "example": "If I were you, I would accept the offer." },
        { "title": "The best course of action", "desc": "recommended approach", "example": "The best course of action is to wait." }
      ]
    },

    "Presenting Examples": {
      "icon": "📝",
      "type": "grouped",
      "items": [
        { "title": "For example / For instance", "desc": "introducing example", "example": "Many cities are growing. London, for example, has grown significantly." },
        { "title": "Such as", "desc": "like", "example": "Many subjects such as maths and science require practice." },
        { "title": "Including", "desc": "among others", "example": "Several countries, including France, have changed policies." },
        { "title": "Particularly / Especially", "desc": "notably", "example": "This is important, particularly for young people." },
        { "title": "In particular", "desc": "specifically", "example": "Many students struggle — teenagers in particular." },
        { "title": "To illustrate this", "desc": "showing example", "example": "To illustrate this, consider the following case." },
        { "title": "Take the case of", "desc": "consider example", "example": "Take the case of Finland's education system." },
        { "title": "A good example of this is", "desc": "demonstrating point", "example": "A good example of this is the recent policy change." },
        { "title": "This can be seen in", "desc": "visible in", "example": "This can be seen in recent statistics." },
        { "title": "As demonstrated by", "desc": "shown by", "example": "As demonstrated by recent research, this is effective." }
      ]
    },

    "Contrasting Ideas": {
      "icon": "🔀",
      "type": "grouped",
      "items": [
        { "title": "However / Nevertheless", "desc": "contrast", "example": "It's expensive. However, it's worth the investment." },
        { "title": "On the contrary", "desc": "opposite meaning", "example": "It's not boring. On the contrary, it's fascinating." },
        { "title": "In contrast / By contrast", "desc": "showing difference", "example": "In contrast, the other method is simpler." },
        { "title": "Although / Though / Even though", "desc": "despite", "example": "Although it's difficult, it's achievable." },
        { "title": "Despite / In spite of", "desc": "regardless of", "example": "Despite the challenges, we succeeded." },
        { "title": "While / Whereas", "desc": "at the same time", "example": "While some agree, others disagree." },
        { "title": "Unlike", "desc": "different from", "example": "Unlike traditional methods, this approach is interactive." },
        { "title": "Conversely", "desc": "opposite situation", "example": "Some prefer online learning. Conversely, others prefer in-person." },
        { "title": "On the other hand", "desc": "alternative view", "example": "It's expensive. On the other hand, the quality is high." },
        { "title": "That said", "desc": "despite previous point", "example": "The method works. That said, it needs practice." }
      ]
    },

    "Summarizing & Concluding": {
      "icon": "🎯",
      "type": "grouped",
      "items": [
        { "title": "In conclusion", "desc": "ending", "example": "In conclusion, education is vital." },
        { "title": "To sum up / To summarize", "desc": "summary", "example": "To sum up, there are three advantages." },
        { "title": "In summary", "desc": "condensed summary", "example": "In summary, both methods have merits." },
        { "title": "Overall", "desc": "general view", "example": "Overall, the results were positive." },
        { "title": "All things considered", "desc": "considering everything", "example": "All things considered, it was a success." },
        { "title": "To conclude", "desc": "final point", "example": "To conclude, immediate action is needed." },
        { "title": "In short / In brief", "desc": "briefly", "example": "In short, the policy didn't work." },
        { "title": "The main point is", "desc": "key idea", "example": "The main point is that change is necessary." },
        { "title": "What this means is", "desc": "implication", "example": "What this means is we need a new approach." },
        { "title": "Ultimately", "desc": "in the end", "example": "Ultimately, the decision is yours." }
      ]
    }
  }
}
