{
  "title": "Academic Expressions (C1–C2)",
  "description": "Advanced academic writing and research vocabulary",
  "categories": {
    "Academic Connectors": {
      "icon": "🔗",
      "type": "grouped",
      "items": [
        { "title": "Furthermore", "desc": "adding extra information", "example": "Furthermore, the results support previous research." },
        { "title": "In addition", "desc": "adding a point", "example": "In addition, several alternative methods were tested." },
        { "title": "Moreover", "desc": "strengthening argument", "example": "Moreover, this approach offers long-term benefits." },
        { "title": "However", "desc": "contrast", "example": "However, the findings cannot be generalized." },
        { "title": "Nevertheless", "desc": "contrast concession", "example": "Nevertheless, the study demonstrates clear trends." },
        { "title": "Consequently", "desc": "result", "example": "Consequently, further investigation is required." }
      ]
    },

    "Academic Verbs": {
      "icon": "🧠",
      "type": "simple",
      "items": [
        "analyse",
        "evaluate",
        "assess",
        "investigate",
        "demonstrate",
        "illustrate",
        "indicate",
        "emphasize",
        "propose",
        "examine",
        "outline",
        "highlight",
        "suggest",
        "consider"
      ]
    },

    "Hedging Language": {
      "icon": "🛡️",
      "type": "grouped",
      "items": [
        { "title": "It is possible that", "desc": "reducing certainty", "example": "It is possible that the data was misinterpreted." },
        { "title": "It seems that", "desc": "tentative claim", "example": "It seems that the participants preferred option B." },
        { "title": "It appears that", "desc": "evidence-based hedge", "example": "It appears that the model performs well." },
        { "title": "The data suggests that", "desc": "implying evidence", "example": "The data suggests that the method is effective." },
        { "title": "It could be argued that", "desc": "soft argument introduction", "example": "It could be argued that the policy is outdated." },
        { "title": "There is some evidence that", "desc": "weak evidence", "example": "There is some evidence that supports this hypothesis." }
      ]
    },

    "Evaluating & Analysing": {
      "icon": "📊",
      "type": "grouped",
      "items": [
        { "title": "A key strength is", "desc": "positive evaluation", "example": "A key strength is the study’s large sample size." },
        { "title": "A major weakness is", "desc": "negative evaluation", "example": "A major weakness is the limited time frame." },
        { "title": "This raises the question of", "desc": "further analysis", "example": "This raises the question of long-term sustainability." },
        { "title": "This suggests that", "desc": "interpreting data", "example": "This suggests that further research is needed." },
        { "title": "This highlights the need for", "desc": "identifying next steps", "example": "This highlights the need for improved procedures." },
        { "title": "This demonstrates that", "desc": "showing significance", "example": "This demonstrates that early intervention is crucial." }
      ]
    },

    "Research Phrases": {
      "icon": "📚",
      "type": "grouped",
      "items": [
        { "title": "According to recent studies", "desc": "referring to research", "example": "According to recent studies, productivity increases with flexibility." },
        { "title": "Previous research has shown", "desc": "background reference", "example": "Previous research has shown that diet affects memory." },
        { "title": "The findings indicate that", "desc": "interpreting results", "example": "The findings indicate that the method is reliable." },
        { "title": "The results suggest that", "desc": "drawing conclusions", "example": "The results suggest that students benefit from feedback." },
        { "title": "This study aims to", "desc": "purpose of study", "example": "This study aims to explore the effects of technology." },
        { "title": "The data was collected from", "desc": "methodology phrase", "example": "The data was collected from 200 participants." }
      ]
    },

    "Argument Structure Phrases": {
      "icon": "🏛️",
      "type": "grouped",
      "items": [
        { "title": "To begin with", "desc": "starting an argument", "example": "To begin with, the evidence is limited." },
        { "title": "Furthermore", "desc": "adding a point", "example": "Furthermore, the cost is relatively low." },
        { "title": "On the other hand", "desc": "presenting contrast", "example": "On the other hand, the project requires training." },
        { "title": "In contrast", "desc": "direct opposition", "example": "In contrast, other studies found no link." },
        { "title": "As a result", "desc": "showing outcome", "example": "As a result, the policy was reconsidered." },
        { "title": "In conclusion", "desc": "ending argument", "example": "In conclusion, the evidence supports reform." }
      ]
    },

    "Formal Synonyms": {
      "icon": "🔤",
      "type": "grouped",
      "items": [
        { "title": "help → assist", "desc": "formal improvement", "example": "The team assisted with the project." },
        { "title": "say → state", "desc": "formal", "example": "The report states that productivity rose." },
        { "title": "look into → investigate", "desc": "formal", "example": "Researchers investigated the issue thoroughly." },
        { "title": "find out → determine", "desc": "formal", "example": "The experiment determined the cause." },
        { "title": "give → provide", "desc": "formal", "example": "The study provides valuable information." },
        { "title": "deal with → address", "desc": "formal", "example": "The proposal addresses key concerns." }
      ]
    },

    "Cohesion Devices": {
      "icon": "🧵",
      "type": "simple",
      "items": [
        "firstly",
        "secondly",
        "finally",
        "in addition",
        "moreover",
        "consequently",
        "therefore",
        "likewise",
        "similarly",
        "in contrast",
        "nevertheless",
        "on the contrary",
        "in summary",
        "overall",
        "ultimately"
      ]
    }
  }
}
