{
  "title": "Essay Structure Practice - B2/C1 Level",
  "setsPerTest": 5,
  "modes": {
    "classic": true,
    "guided": true,
    "essay": true
  },
  "sets": [
    {
      "setNumber": 1,
      "mode": "discrete",
      "topic": "Advantages (1)",
      "words": ["key advantage", "main benefit", "significant plus", "major strength"],
      "sentences": [
        {
          "text": "The _____ of remote work is flexibility.",
          "correct": 0,
          "hint": "Use the phrase with 'key' for the primary advantage"
        },
        {
          "text": "The _____ is reduced commuting time.",
          "correct": 1,
          "hint": "Choose the most common word for a positive feature"
        },
        {
          "text": "A _____ is the cost savings involved.",
          "correct": 2,
          "hint": "Pick the informal phrase for an important advantage"
        },
        {
          "text": "Its _____ lies in accessibility for all users.",
          "correct": 3,
          "hint": "Use the phrase emphasizing a core positive quality"
        }
      ]
    },
    {
      "setNumber": 2,
      "mode": "discrete",
      "topic": "Advantages (2)",
      "words": ["obvious advantage", "clear benefit", "notable merit", "distinct advantage"],
      "sentences": [
        {
          "text": "An _____ is the environmental benefit.",
          "correct": 0,
          "hint": "Use the phrase for something visibly or clearly advantageous"
        },
        {
          "text": "The _____ is improved work-life balance.",
          "correct": 1,
          "hint": "Choose the phrase for an evident positive outcome"
        },
        {
          "text": "A _____ is its user-friendly design.",
          "correct": 2,
          "hint": "Pick the formal word for a worthy quality or feature"
        },
        {
          "text": "Its _____ over competitors is speed.",
          "correct": 3,
          "hint": "Use the phrase meaning a clear difference that's better"
        }
      ]
    },
    {
      "setNumber": 3,
      "mode": "discrete",
      "topic": "Disadvantages (1)",
      "words": ["main drawback", "significant downside", "major weakness", "serious limitation"],
      "sentences": [
        {
          "text": "The _____ is the high initial cost.",
          "correct": 0,
          "hint": "Use the phrase for the primary negative aspect"
        },
        {
          "text": "A _____ is the lack of face-to-face interaction.",
          "correct": 1,
          "hint": "Choose the phrase for an important negative consequence"
        },
        {
          "text": "Its _____ is the complexity of operation.",
          "correct": 2,
          "hint": "Pick the phrase for an inherent flaw or vulnerable point"
        },
        {
          "text": "A _____ is the restricted functionality.",
          "correct": 3,
          "hint": "Use the phrase for a significant constraint or restriction"
        }
      ]
    },
    {
      "setNumber": 4,
      "mode": "discrete",
      "topic": "Disadvantages (2)",
      "words": ["key problem", "notable disadvantage", "clear flaw", "primary concern"],
      "sentences": [
        {
          "text": "The _____ is insufficient data security.",
          "correct": 0,
          "hint": "Use the phrase for the main problematic issue"
        },
        {
          "text": "A _____ is its dependence on technology.",
          "correct": 1,
          "hint": "Choose the phrase for a significant negative feature"
        },
        {
          "text": "The _____ in this approach is its rigidity.",
          "correct": 2,
          "hint": "Pick the phrase for an obvious defect or imperfection"
        },
        {
          "text": "The _____ is potential job displacement.",
          "correct": 3,
          "hint": "Use the phrase for the main worry or issue"
        }
      ]
    },
    {
      "setNumber": 5,
      "mode": "essay",
      "topic": "Electric Vehicles - Advantages & Disadvantages",
      "context": "Body paragraphs from a B2 essay discussing pros and cons of electric vehicles",
      "paragraph": "Electric vehicles offer compelling benefits for modern transportation. The ___1___ is their environmental impact—they produce zero direct emissions. A ___2___ is significantly lower operating costs compared to petrol vehicles. Furthermore, the ___3___ lies in reduced noise pollution in urban areas. However, several challenges remain. The ___4___ is the limited charging infrastructure in many regions. A ___5___ is the higher purchase price, which deters many consumers. The ___6___ in current battery technology is the long charging time. A ___7___ is range anxiety, as most models cannot match the distance of traditional vehicles. Despite these issues, the ___8___ over conventional cars in environmental terms makes them increasingly attractive.",
      "wordBank": [
        "key advantage",
        "main benefit",
        "significant plus",
        "major strength",
        "distinct advantage",
        "main drawback",
        "significant downside",
        "major weakness",
        "serious limitation",
        "key problem",
        "notable disadvantage",
        "clear flaw",
        "primary concern",
        "obvious advantage",
        "clear benefit"
      ],
      "answers": {
        "1": 1,
        "2": 2,
        "3": 3,
        "4": 9,
        "5": 5,
        "6": 11,
        "7": 12,
        "8": 4
      },
      "hints": {
        "1": "Use the most common positive phrase",
        "2": "Add another advantage informally",
        "3": "Describe inherent positive quality",
        "4": "Introduce the main problem",
        "5": "Present the primary negative aspect",
        "6": "Point out a defect in technology",
        "7": "State the main worry",
        "8": "Emphasize clear superiority"
      }
    },
    {
      "setNumber": 6,
      "mode": "discrete",
      "topic": "Problem-Solution: Problems (1)",
      "words": ["serious obstacle", "major challenge", "significant issue", "pressing concern"],
      "sentences": [
        {
          "text": "The lack of funding poses a _____ to progress.",
          "correct": 0,
          "hint": "Use the phrase for something blocking the way forward"
        },
        {
          "text": "Climate change represents a _____ for humanity.",
          "correct": 1,
          "hint": "Choose the phrase for a difficult task requiring effort"
        },
        {
          "text": "Inequality remains a _____ in modern society.",
          "correct": 2,
          "hint": "Pick the phrase for an important problem or topic"
        },
        {
          "text": "Healthcare access is a _____ in rural areas.",
          "correct": 3,
          "hint": "Use the phrase for an urgent worry requiring attention"
        }
      ]
    },
    {
      "setNumber": 7,
      "mode": "discrete",
      "topic": "Problem-Solution: Problems (2)",
      "words": ["crucial problem", "critical difficulty", "fundamental flaw", "substantial barrier"],
      "sentences": [
        {
          "text": "Data privacy has become a _____ online.",
          "correct": 0,
          "hint": "Use the phrase for a problem of vital importance"
        },
        {
          "text": "The skills gap presents a _____ for employers.",
          "correct": 1,
          "hint": "Choose the phrase for a serious, urgent challenge"
        },
        {
          "text": "The _____ in the system is lack of accountability.",
          "correct": 2,
          "hint": "Pick the phrase for a basic, underlying defect"
        },
        {
          "text": "Infrastructure decay creates a _____ to development.",
          "correct": 3,
          "hint": "Use the phrase for a significant obstacle blocking progress"
        }
      ]
    },
    {
      "setNumber": 8,
      "mode": "discrete",
      "topic": "Problem-Solution: Solutions (1)",
      "words": ["effective solution", "viable approach", "practical measure", "workable strategy"],
      "sentences": [
        {
          "text": "An _____ would be investing in renewable energy.",
          "correct": 0,
          "hint": "Use the phrase for a solution that produces results"
        },
        {
          "text": "A _____ is to improve public transport systems.",
          "correct": 1,
          "hint": "Choose the phrase for a feasible method or way"
        },
        {
          "text": "One _____ is implementing stricter regulations.",
          "correct": 2,
          "hint": "Pick the phrase for a realistic action or step"
        },
        {
          "text": "A _____ involves collaboration between sectors.",
          "correct": 3,
          "hint": "Use the phrase for a plan that can work in practice"
        }
      ]
    },
    {
      "setNumber": 9,
      "mode": "discrete",
      "topic": "Problem-Solution: Solutions (2)",
      "words": ["feasible option", "realistic answer", "sensible response", "pragmatic method"],
      "sentences": [
        {
          "text": "A _____ is to provide subsidies for education.",
          "correct": 0,
          "hint": "Use the phrase for a choice that's possible to implement"
        },
        {
          "text": "The most _____ is prevention through education.",
          "correct": 1,
          "hint": "Choose the phrase for a practical, achievable solution"
        },
        {
          "text": "A _____ would be increasing transparency.",
          "correct": 2,
          "hint": "Pick the phrase for a reasonable, logical reaction"
        },
        {
          "text": "The _____ is gradual, phased implementation.",
          "correct": 3,
          "hint": "Use the phrase for a practical, realistic approach"
        }
      ]
    },
    {
      "setNumber": 10,
      "mode": "essay",
      "topic": "Urban Traffic Congestion - Problem-Solution",
      "context": "Complete B2 essay paragraph presenting problems and solutions",
      "paragraph": "Urban traffic congestion represents a ___1___ for cities worldwide. This ___2___ to economic productivity costs billions annually in lost time. A ___3___ lies in inadequate investment in public infrastructure over past decades. The ___4___ is that current road capacity cannot meet demand. Addressing this crisis requires multiple interventions. An ___5___ would be expanding metro and bus rapid transit systems. A ___6___ involves implementing congestion pricing in city centers, as demonstrated successfully in London and Singapore. Furthermore, a ___7___ is to incentivize remote work, reducing daily commuter numbers. The most ___8___ combines all these measures with improved urban planning to create sustainable, livable cities.",
      "wordBank": [
        "serious obstacle",
        "major challenge",
        "significant issue",
        "pressing concern",
        "crucial problem",
        "fundamental flaw",
        "effective solution",
        "viable approach",
        "practical measure",
        "workable strategy",
        "feasible option",
        "realistic answer",
        "sensible response",
        "pragmatic method",
        "clear flaw"
      ],
      "answers": {
        "1": 1,
        "2": 4,
        "3": 5,
        "4": 2,
        "5": 6,
        "6": 7,
        "7": 8,
        "8": 9
      },
      "hints": {
        "1": "Describe the difficult task cities face",
        "2": "Name the vital problem being discussed",
        "3": "Identify the underlying defect",
        "4": "State the important problem",
        "5": "Propose a results-producing solution",
        "6": "Suggest a feasible method",
        "7": "Recommend a realistic action",
        "8": "Conclude with a plan that works"
      }
    },
    {
      "setNumber": 11,
      "mode": "discrete",
      "topic": "Cause & Effect: Causes (1)",
      "words": ["caused by", "attributed to", "a result of", "rooted in"],
      "sentences": [
        {
          "text": "The housing crisis is _____ insufficient construction.",
          "correct": 0,
          "hint": "Use the most direct phrase for what made something happen"
        },
        {
          "text": "The success is often _____ careful planning.",
          "correct": 1,
          "hint": "Choose the phrase for crediting something as the cause"
        },
        {
          "text": "The economic downturn is _____ poor fiscal policies.",
          "correct": 2,
          "hint": "Pick the phrase meaning 'resulting from' or 'consequence of'"
        },
        {
          "text": "The crisis is _____ decades of neglect.",
          "correct": 3,
          "hint": "Use the phrase for deep, fundamental origins"
        }
      ]
    },
    {
      "setNumber": 12,
      "mode": "discrete",
      "topic": "Cause & Effect: Causes (2)",
      "words": ["stems from", "arises from", "due to", "owing to"],
      "sentences": [
        {
          "text": "The problem _____ fundamental misunderstanding.",
          "correct": 0,
          "hint": "Use the phrase meaning 'originates from' or 'has its source in'"
        },
        {
          "text": "The conflict _____ competing interests.",
          "correct": 1,
          "hint": "Choose the phrase meaning 'emerges from' or 'comes from'"
        },
        {
          "text": "The delay was _____ technical difficulties.",
          "correct": 2,
          "hint": "Pick the most common two-word preposition for causes"
        },
        {
          "text": "The closure was _____ safety concerns.",
          "correct": 3,
          "hint": "Use the more formal alternative meaning 'because of'"
        }
      ]
    },
    {
      "setNumber": 13,
      "mode": "discrete",
      "topic": "Cause & Effect: Effects (1)",
      "words": ["has prompted", "sparked off", "has aroused", "had an impact on"],
      "sentences": [
        {
          "text": "The scandal _____ widespread debate about reform.",
          "correct": 0,
          "hint": "Use the phrase for causing something to begin or happen"
        },
        {
          "text": "The policy _____ angry reactions from the public.",
          "correct": 1,
          "hint": "Choose the phrase for suddenly triggering or igniting"
        },
        {
          "text": "This decision _____ widespread opposition.",
          "correct": 2,
          "hint": "Pick the phrase for stirring up or awakening feelings"
        },
        {
          "text": "The recession _____ the entire economy.",
          "correct": 3,
          "hint": "Use the phrase for having an effect or influence on"
        }
      ]
    },
    {
      "setNumber": 14,
      "mode": "discrete",
      "topic": "Cause & Effect: Effects (2)",
      "words": ["will affect", "results in", "leads to", "gives rise to"],
      "sentences": [
        {
          "text": "This _____ the local industry significantly.",
          "correct": 0,
          "hint": "Use the simple future phrase for impact or influence"
        },
        {
          "text": "Poor planning _____ inefficiency and waste.",
          "correct": 1,
          "hint": "Choose the phrase for direct consequences or outcomes"
        },
        {
          "text": "Climate change _____ extreme weather events.",
          "correct": 2,
          "hint": "Pick the phrase meaning 'causes' or 'brings about'"
        },
        {
          "text": "Inequality _____ social tensions.",
          "correct": 3,
          "hint": "Use the formal phrase meaning 'causes to exist' or 'produces'"
        }
      ]
    },
    {
      "setNumber": 15,
      "mode": "essay",
      "topic": "Social Media Impact - Cause & Effect",
      "context": "Body paragraphs from a B2 essay analyzing social media's effects on society",
      "paragraph": "The rise of social media ___1___ profound changes in human communication. This transformation ___2___ several interconnected factors, including technological advancement and changing social norms. The widespread adoption of smartphones ___3___ constant connectivity, which ___4___ both benefits and challenges. On the positive side, digital platforms ___5___ unprecedented opportunities for global networking and information sharing. However, excessive use ___6___ documented mental health concerns, particularly among young people. The phenomenon of 'doomscrolling' ___7___ increased anxiety and depression. Research shows that social comparison ___8___ reduced self-esteem and wellbeing. These effects demonstrate how technology reshapes fundamental aspects of human behavior and psychology.",
      "wordBank": [
        "caused by",
        "attributed to",
        "a result of",
        "rooted in",
        "stems from",
        "arises from",
        "has prompted",
        "sparked off",
        "has aroused",
        "had an impact on",
        "results in",
        "leads to",
        "gives rise to",
        "will affect",
        "creates"
      ],
      "answers": {
        "1": 6,
        "2": 4,
        "3": 14,
        "4": 12,
        "5": 10,
        "6": 11,
        "7": 8,
        "8": 10
      },
      "hints": {
        "1": "Show how social media triggered changes",
        "2": "Explain the deep origins",
        "3": "Show what smartphones create",
        "4": "Describe what connectivity produces",
        "5": "Show the outcome digital platforms produce",
        "6": "Connect usage to mental health outcomes",
        "7": "Show what the phenomenon stirs up",
        "8": "Connect comparison to its consequence"
      }
    }
  ]
}
